{
    "hash": "b'1b66ee0b8373f60b3ab3155ec2f9a96ec42d2f797eec088224b12b07fbb20745b34d3bdc67e5d6918e7d195921190592688561dda02c5685919c537409637ae5'",
    "conditional": {
        "loot": {
            "max_items": 1,
            "silver": 99,
            "items_possible": [
                "health_potion.json",
                "scroll_of_resurrection.json",
                "scroll_of_identify.json"
            ],
            "always_drops": [],
            "copper": 99,
            "gold": 10
        },
        "abilities": {
            "move silently": 60,
            "read languages": 0,
            "hide in shadows": 45,
            "pick pockets": 15,
            "open locks": 10,
            "find-remove traps": 5,
            "climb walls": 60,
            "detect noise": 15
        },
        "orientation": " aggressive",
        "shields": false,
        "armor_types": 3,
        "events": {
            "oninteract": "",
            "oninspect": ""
        }
    },
    "core": {
        "class": {
            "class": "thief",
            "parent": "rogue"
        },
        "abilities": {
            "str": 10,
            "int": 16,
            "dex": 19,
            "cha": 9,
            "wis": 8,
            "con": 12
        },
        "lightradius": 0,
        "combat": {
            "level-hitdice": 4,
            "hitpoints": 5,
            "max_hp": 32
        },
        "location": {
            "y": 5,
            "map": "black_tower.json",
            "x": 2
        },
        "icon": "avatars/floop.png",
        "inventory": {
            "pack": [],
            "spells_memorized": [],
            "spells": [],
            "equiped": {
                "hands": {
                    "events": {
                        "onunequip": "",
                        "onround": "",
                        "onuse": "",
                        "onequip": "",
                        "onpickup": "",
                        "ondrop": "campaign.warning('%s has dropped %s' % (player.displayname(), item.displayname()))",
                        "onfinish": ""
                    },
                    "conditional": {
                        "ac": 0.4,
                        "slot": "hands",
                        "material": "leather"
                    },
                    "core": {
                        "description": "",
                        "icon": "icons/tough_leather_gloves.png",
                        "identified": true,
                        "lightradius": 0,
                        "charges": 0,
                        "rounds_per_charge": 0,
                        "name": "Crocodile Leather Gloves",
                        "size": "small",
                        "current_rounds_performed": 0,
                        "weight": 1,
                        "type": "armor",
                        "price": {
                            "silver": 0,
                            "copper": 0,
                            "gold": 1
                        },
                        "in_use": false
                    }
                },
                "rightfinger": {},
                "leftfinger": {},
                "feet": {
                    "events": {
                        "onround": "",
                        "onuse": "",
                        "onequip": "",
                        "onpickup": "",
                        "ondrop": "campaign.warning('%s has dropped %s' % (player.displayname(), item.displayname()))",
                        "onfinish": ""
                    },
                    "conditional": {
                        "ac": 0.2,
                        "slot": "feet",
                        "material": "leather"
                    },
                    "core": {
                        "description": "",
                        "icon": "icons/leather_boots.png",
                        "identified": true,
                        "rounds_per_charge": 0,
                        "charges": 0,
                        "name": "Leather Boots",
                        "size": "small",
                        "current_rounds_performed": 0,
                        "weight": 1,
                        "type": "armor",
                        "price": {
                            "silver": 0,
                            "copper": 0,
                            "gold": 1
                        },
                        "in_use": false
                    }
                },
                "righthand": {
                    "events": {
                        "onunequip": "",
                        "onfinish": "",
                        "onuse": "",
                        "onequip": "",
                        "onpickup": "",
                        "ondrop": "",
                        "onround": ""
                    },
                    "conditional": {
                        "to_hit": 0,
                        "slot": "righthand",
                        "range": "short",
                        "save_against": "none",
                        "weapon_type": "melee",
                        "damage_type": "slice",
                        "dmg": "1d4"
                    },
                    "core": {
                        "description": "",
                        "icon": "icons/silver.png",
                        "identified": true,
                        "lightradius": 0,
                        "charges": 0,
                        "rounds_per_charge": 0,
                        "name": "Broken Bottle",
                        "size": "small",
                        "current_rounds_performed": 0,
                        "weight": 0,
                        "type": "weapon",
                        "price": {
                            "silver": 0,
                            "copper": 0,
                            "gold": 0
                        },
                        "in_use": false
                    }
                },
                "neck": {},
                "legs": {
                    "events": {
                        "onunequip": "",
                        "onfinish": "",
                        "onuse": "",
                        "onequip": "",
                        "onpickup": "",
                        "ondrop": "campaign.warning('%s has dropped %s' % (player.displayname(), item.displayname()))",
                        "onround": ""
                    },
                    "conditional": {
                        "ac": 0.8,
                        "slot": "legs",
                        "material": "leather"
                    },
                    "core": {
                        "description": "",
                        "lightradius": 0,
                        "identified": true,
                        "rounds_per_charge": 0,
                        "type": "armor",
                        "name": "Leather Leggings",
                        "weight": 2,
                        "size": "large",
                        "current_rounds_performed": 0,
                        "icon": "icons/tough_leather_boots.png",
                        "price": {
                            "silver": 50,
                            "copper": 0,
                            "gold": 1
                        },
                        "charges": 0,
                        "in_use": false
                    }
                },
                "head": {
                    "events": {
                        "onunequip": "",
                        "onfinish": "",
                        "onuse": "",
                        "onequip": "",
                        "onpickup": "",
                        "ondrop": "campaign.warning('%s has dropped %s' % (player.displayname(), item.displayname()))",
                        "onround": ""
                    },
                    "conditional": {
                        "ac": 1.6,
                        "slot": "head",
                        "material": "leather"
                    },
                    "core": {
                        "lightradius": 0,
                        "icon": "icons/tough_leather_helm.png",
                        "in_use": false,
                        "identified": true,
                        "type": "armor",
                        "charges": 0,
                        "description": "",
                        "weight": 2,
                        "size": "small",
                        "current_rounds_performed": 0,
                        "name": "Crocodile Leather Helm",
                        "price": {
                            "silver": 0,
                            "copper": 0,
                            "gold": 1
                        },
                        "rounds_per_charge": 0
                    }
                },
                "wrists": {},
                "lefthand": {
                    "events": {
                        "onunequip": "",
                        "onfinish": "",
                        "onuse": "",
                        "onequip": "",
                        "onpickup": "",
                        "ondrop": "",
                        "onround": ""
                    },
                    "conditional": {
                        "to_hit": "+1",
                        "slot": "lefthand",
                        "range": "short",
                        "save_against": "none",
                        "weapon_type": "melee",
                        "events": {
                            "onstrike": ""
                        },
                        "damage_type": "stab",
                        "dmg": 8
                    },
                    "core": {
                        "description": "",
                        "lightradius": 0,
                        "icon": "",
                        "size": "medium",
                        "type": "weapon",
                        "charges": 0,
                        "identified": true,
                        "weight": 0,
                        "name": "Bear Bite",
                        "current_rounds_performed": 0,
                        "in_use": false,
                        "rounds_per_charge": 0,
                        "price": {
                            "silver": 0,
                            "copper": 0,
                            "gold": 0
                        }
                    }
                },
                "gloves": {},
                "chest": {
                    "events": {
                        "onunequip": "",
                        "onround": "",
                        "onuse": "",
                        "onequip": "",
                        "onpickup": "",
                        "ondrop": "campaign.warning('%s has dropped %s' % (player.displayname(), item.displayname()))",
                        "onfinish": ""
                    },
                    "conditional": {
                        "ac": 2,
                        "slot": "chest",
                        "material": "leather"
                    },
                    "core": {
                        "description": "",
                        "icon": "icons/tough_leather_armor.png",
                        "in_use": false,
                        "identified": true,
                        "lightradius": 0,
                        "size": "medium",
                        "charges": 0,
                        "rounds_per_charge": 0,
                        "name": "Crocodile Leather Chest",
                        "current_rounds_performed": 0,
                        "weight": 8,
                        "type": "armor",
                        "price": {
                            "silver": 50,
                            "copper": 0,
                            "gold": 1
                        }
                    }
                }
            },
            "money": {
                "silver": 0,
                "copper": 0,
                "gold": 0
            }
        },
        "personal": {
            "sex": "female",
            "backstory": "Evil  vampire-bat",
            "name": {
                "first": "Floop",
                "last": "Floop"
            },
            "race": "creature",
            "xp": 0,
            "alignment": {
                "law": "chaotic",
                "social": "evil"
            }
        },
        "type": "npc"
    }
}